envelope.v


module envelope(
    input clk,
    input loop,              // Controls whether the volume loops or not
    input disableFlag,       // Controls the disable
    input resetFlag,         // resetFlag==0 if the length counter is written to
    input[3:0] n,            // Period of the counter_clk. Volume defaults to n when disabled
    output reg[3:0] volume   // Output
);
reg reset;
reg[3:0] counter;
wire counter_clk; 

clkDivider divider(clk, reset, n+4'b1, counter_clk);

always @(posedge clk) begin
    if(resetFlag) begin
        counter <= 4'd15;
        reset <= 1;
    end
    else
        reset <= 0;
    if(disableFlag)
        volume <= n;
    else
        volume <= counter;
end

always @(posedge counter_clk) begin
    // If loop is set and counter is zero then it loops back to 15
    // If loop is not enabled and counter is not zero it decrements
    // If loop is not enabled, counter will decrease until it is zero
    if(loop && (counter == 0)) 
        counter <= 4'd15;
    if(counter !== 0)
        counter <= counter - 1;
end

endmodule

// Clk Divider Module, takes in clk and N(period of new clk)
// Ouputs new clk with period of N clk
module clkDivider(
    input clk,
    input rst,
    input[3:0] N,
    output clk_out
);
reg[3:0] n;
reg[3:0] r_reg;
wire[3:0] r_next;
reg clk_track;

initial begin
    n <= N/2;
    r_reg <= 0;
    clk_track <= 1'b0;
end

always @(posedge clk or posedge rst) begin
    if(rst) begin
        n <= N/2;
        r_reg <= 0;
        clk_track <= 1'b0;
    end
    else if(r_next == n) begin
        r_reg <= 0;
        clk_track <= ~clk_track;
    end
    else
        r_reg <= r_next;
end
assign r_next = r_reg+1;
assign clk_out = clk_track;
endmodule

envelope.t.v
`include "envelope.v"

module envelopeTest(); 
reg clk;
reg loop;
reg disableFlag;
reg resetFlag;
reg[3:0] n;
wire[3:0] volume;

initial
    clk <= 0;

always begin
    #5000
    clk <= ~clk;
end

envelope envy(clk, loop, disableFlag, resetFlag, n, volume);

initial begin
    $dumpfile("envelope.vcd");
    $dumpvars();
    assign loop = 1'b0;
    assign disableFlag = 1'b0;
    assign n = 4'd3;
    assign resetFlag = 1'b1;
    #10000
    assign resetFlag = 1'b0;
    assign loop = 1'b1;
    #500000
    assign loop = 1'b0;
    #100000
    assign disableFlag = 1'b1;
    #1000000
    $finish();
end

endmodule

envelope.vcd
$date
	Thu Dec  6 23:10:37 2018
$end
$version
	Icarus Verilog
$end
$timescale
	1s
$end
$scope module envelopeTest $end
$var wire 4 ! volume [3:0] $end
$var reg 1 " clk $end
$var reg 1 # disableFlag $end
$var reg 1 $ loop $end
$var reg 4 % n [3:0] $end
$var reg 1 & resetFlag $end
$scope module envy $end
$var wire 1 " clk $end
$var wire 1 # disableFlag $end
$var wire 1 $ loop $end
$var wire 4 ' n [3:0] $end
$var wire 1 & resetFlag $end
$var wire 1 ( counter_clk $end
$var reg 4 ) counter [3:0] $end
$var reg 1 * reset $end
$var reg 4 + volume [3:0] $end
$scope module divider $end
$var wire 4 , N [3:0] $end
$var wire 1 " clk $end
$var wire 1 ( clk_out $end
$var wire 1 * rst $end
$var wire 4 - r_next [3:0] $end
$var reg 1 . clk_track $end
$var reg 4 / n [3:0] $end
$var reg 4 0 r_reg [3:0] $end
$upscope $end
$upscope $end
$upscope $end
$enddefinitions $end
#0
$dumpvars
b0 0
bx /
0.
b1 -
b100 ,
bx +
x*
bx )
0(
b11 '
1&
b11 %
0$
0#
0"
bx !
$end
#5000
b10 /
b1 -
b0 0
1*
b1111 )
1"
#10000
0"
1$
0&
#15000
b1111 !
b1111 +
0*
1"
#20000
0"
#25000
b10 -
b1 0
1"
#30000
0"
#35000
b1110 )
1(
1.
b1 -
b0 0
1"
#40000
0"
#45000
b10 -
b1 0
b1110 !
b1110 +
1"
#50000
0"
#55000
0(
0.
b1 -
b0 0
1"
#60000
0"
#65000
b10 -
b1 0
1"
#70000
0"
#75000
b1101 )
1(
1.
b1 -
b0 0
1"
#80000
0"
#85000
b10 -
b1 0
b1101 !
b1101 +
1"
#90000
0"
#95000
0(
0.
b1 -
b0 0
1"
#100000
0"
#105000
b10 -
b1 0
1"
#110000
0"
#115000
b1100 )
1(
1.
b1 -
b0 0
1"
#120000
0"
#125000
b10 -
b1 0
b1100 !
b1100 +
1"
#130000
0"
#135000
0(
0.
b1 -
b0 0
1"
#140000
0"
#145000
b10 -
b1 0
1"
#150000
0"
#155000
b1011 )
1(
1.
b1 -
b0 0
1"
#160000
0"
#165000
b10 -
b1 0
b1011 !
b1011 +
1"
#170000
0"
#175000
0(
0.
b1 -
b0 0
1"
#180000
0"
#185000
b10 -
b1 0
1"
#190000
0"
#195000
b1010 )
1(
1.
b1 -
b0 0
1"
#200000
0"
#205000
b10 -
b1 0
b1010 !
b1010 +
1"
#210000
0"
#215000
0(
0.
b1 -
b0 0
1"
#220000
0"
#225000
b10 -
b1 0
1"
#230000
0"
#235000
b1001 )
1(
1.
b1 -
b0 0
1"
#240000
0"
#245000
b10 -
b1 0
b1001 !
b1001 +
1"
#250000
0"
#255000
0(
0.
b1 -
b0 0
1"
#260000
0"
#265000
b10 -
b1 0
1"
#270000
0"
#275000
b1000 )
1(
1.
b1 -
b0 0
1"
#280000
0"
#285000
b10 -
b1 0
b1000 !
b1000 +
1"
#290000
0"
#295000
0(
0.
b1 -
b0 0
1"
#300000
0"
#305000
b10 -
b1 0
1"
#310000
0"
#315000
b111 )
1(
1.
b1 -
b0 0
1"
#320000
0"
#325000
b10 -
b1 0
b111 !
b111 +
1"
#330000
0"
#335000
0(
0.
b1 -
b0 0
1"
#340000
0"
#345000
b10 -
b1 0
1"
#350000
0"
#355000
b110 )
1(
1.
b1 -
b0 0
1"
#360000
0"
#365000
b10 -
b1 0
b110 !
b110 +
1"
#370000
0"
#375000
0(
0.
b1 -
b0 0
1"
#380000
0"
#385000
b10 -
b1 0
1"
#390000
0"
#395000
b101 )
1(
1.
b1 -
b0 0
1"
#400000
0"
#405000
b10 -
b1 0
b101 !
b101 +
1"
#410000
0"
#415000
0(
0.
b1 -
b0 0
1"
#420000
0"
#425000
b10 -
b1 0
1"
#430000
0"
#435000
b100 )
1(
1.
b1 -
b0 0
1"
#440000
0"
#445000
b10 -
b1 0
b100 !
b100 +
1"
#450000
0"
#455000
0(
0.
b1 -
b0 0
1"
#460000
0"
#465000
b10 -
b1 0
1"
#470000
0"
#475000
b11 )
1(
1.
b1 -
b0 0
1"
#480000
0"
#485000
b10 -
b1 0
b11 !
b11 +
1"
#490000
0"
#495000
0(
0.
b1 -
b0 0
1"
#500000
0"
#505000
b10 -
b1 0
1"
#510000
0"
0$
#515000
b10 )
1(
1.
b1 -
b0 0
1"
#520000
0"
#525000
b10 -
b1 0
b10 !
b10 +
1"
#530000
0"
#535000
0(
0.
b1 -
b0 0
1"
#540000
0"
#545000
b10 -
b1 0
1"
#550000
0"
#555000
b1 )
1(
1.
b1 -
b0 0
1"
#560000
0"
#565000
b10 -
b1 0
b1 !
b1 +
1"
#570000
0"
#575000
0(
0.
b1 -
b0 0
1"
#580000
0"
#585000
b10 -
b1 0
1"
#590000
0"
#595000
b0 )
1(
1.
b1 -
b0 0
1"
#600000
0"
#605000
b10 -
b1 0
b0 !
b0 +
1"
#610000
0"
1#
#615000
0(
0.
b1 -
b0 0
b11 !
b11 +
1"
#620000
0"
#625000
b10 -
b1 0
1"
#630000
0"
#635000
1(
1.
b1 -
b0 0
1"
#640000
0"
#645000
b10 -
b1 0
1"
#650000
0"
#655000
0(
0.
b1 -
b0 0
1"
#660000
0"
#665000
b10 -
b1 0
1"
#670000
0"
#675000
1(
1.
b1 -
b0 0
1"
#680000
0"
#685000
b10 -
b1 0
1"
#690000
0"
#695000
0(
0.
b1 -
b0 0
1"
#700000
0"
#705000
b10 -
b1 0
1"
#710000
0"
#715000
1(
1.
b1 -
b0 0
1"
#720000
0"
#725000
b10 -
b1 0
1"
#730000
0"
#735000
0(
0.
b1 -
b0 0
1"
#740000
0"
#745000
b10 -
b1 0
1"
#750000
0"
#755000
1(
1.
b1 -
b0 0
1"
#760000
0"
#765000
b10 -
b1 0
1"
#770000
0"
#775000
0(
0.
b1 -
b0 0
1"
#780000
0"
#785000
b10 -
b1 0
1"
#790000
0"
#795000
1(
1.
b1 -
b0 0
1"
#800000
0"
#805000
b10 -
b1 0
1"
#810000
0"
#815000
0(
0.
b1 -
b0 0
1"
#820000
0"
#825000
b10 -
b1 0
1"
#830000
0"
#835000
1(
1.
b1 -
b0 0
1"
#840000
0"
#845000
b10 -
b1 0
1"
#850000
0"
#855000
0(
0.
b1 -
b0 0
1"
#860000
0"
#865000
b10 -
b1 0
1"
#870000
0"
#875000
1(
1.
b1 -
b0 0
1"
#880000
0"
#885000
b10 -
b1 0
1"
#890000
0"
#895000
0(
0.
b1 -
b0 0
1"
#900000
0"
#905000
b10 -
b1 0
1"
#910000
0"
#915000
1(
1.
b1 -
b0 0
1"
#920000
0"
#925000
b10 -
b1 0
1"
#930000
0"
#935000
0(
0.
b1 -
b0 0
1"
#940000
0"
#945000
b10 -
b1 0
1"
#950000
0"
#955000
1(
1.
b1 -
b0 0
1"
#960000
0"
#965000
b10 -
b1 0
1"
#970000
0"
#975000
0(
0.
b1 -
b0 0
1"
#980000
0"
#985000
b10 -
b1 0
1"
#990000
0"
#995000
1(
1.
b1 -
b0 0
1"
#1000000
0"
#1005000
b10 -
b1 0
1"
#1010000
0"
#1015000
0(
0.
b1 -
b0 0
1"
#1020000
0"
#1025000
b10 -
b1 0
1"
#1030000
0"
#1035000
1(
1.
b1 -
b0 0
1"
#1040000
0"
#1045000
b10 -
b1 0
1"
#1050000
0"
#1055000
0(
0.
b1 -
b0 0
1"
#1060000
0"
#1065000
b10 -
b1 0
1"
#1070000
0"
#1075000
1(
1.
b1 -
b0 0
1"
#1080000
0"
#1085000
b10 -
b1 0
1"
#1090000
0"
#1095000
0(
0.
b1 -
b0 0
1"
#1100000
0"
#1105000
b10 -
b1 0
1"
#1110000
0"
#1115000
1(
1.
b1 -
b0 0
1"
#1120000
0"
#1125000
b10 -
b1 0
1"
#1130000
0"
#1135000
0(
0.
b1 -
b0 0
1"
#1140000
0"
#1145000
b10 -
b1 0
1"
#1150000
0"
#1155000
1(
1.
b1 -
b0 0
1"
#1160000
0"
#1165000
b10 -
b1 0
1"
#1170000
0"
#1175000
0(
0.
b1 -
b0 0
1"
#1180000
0"
#1185000
b10 -
b1 0
1"
#1190000
0"
#1195000
1(
1.
b1 -
b0 0
1"
#1200000
0"
#1205000
b10 -
b1 0
1"
#1210000
0"
#1215000
0(
0.
b1 -
b0 0
1"
#1220000
0"
#1225000
b10 -
b1 0
1"
#1230000
0"
#1235000
1(
1.
b1 -
b0 0
1"
#1240000
0"
#1245000
b10 -
b1 0
1"
#1250000
0"
#1255000
0(
0.
b1 -
b0 0
1"
#1260000
0"
#1265000
b10 -
b1 0
1"
#1270000
0"
#1275000
1(
1.
b1 -
b0 0
1"
#1280000
0"
#1285000
b10 -
b1 0
1"
#1290000
0"
#1295000
0(
0.
b1 -
b0 0
1"
#1300000
0"
#1305000
b10 -
b1 0
1"
#1310000
0"
#1315000
1(
1.
b1 -
b0 0
1"
#1320000
0"
#1325000
b10 -
b1 0
1"
#1330000
0"
#1335000
0(
0.
b1 -
b0 0
1"
#1340000
0"
#1345000
b10 -
b1 0
1"
#1350000
0"
#1355000
1(
1.
b1 -
b0 0
1"
#1360000
0"
#1365000
b10 -
b1 0
1"
#1370000
0"
#1375000
0(
0.
b1 -
b0 0
1"
#1380000
0"
#1385000
b10 -
b1 0
1"
#1390000
0"
#1395000
1(
1.
b1 -
b0 0
1"
#1400000
0"
#1405000
b10 -
b1 0
1"
#1410000
0"
#1415000
0(
0.
b1 -
b0 0
1"
#1420000
0"
#1425000
b10 -
b1 0
1"
#1430000
0"
#1435000
1(
1.
b1 -
b0 0
1"
#1440000
0"
#1445000
b10 -
b1 0
1"
#1450000
0"
#1455000
0(
0.
b1 -
b0 0
1"
#1460000
0"
#1465000
b10 -
b1 0
1"
#1470000
0"
#1475000
1(
1.
b1 -
b0 0
1"
#1480000
0"
#1485000
b10 -
b1 0
1"
#1490000
0"
#1495000
0(
0.
b1 -
b0 0
1"
#1500000
0"
#1505000
b10 -
b1 0
1"
#1510000
0"
#1515000
1(
1.
b1 -
b0 0
1"
#1520000
0"
#1525000
b10 -
b1 0
1"
#1530000
0"
#1535000
0(
0.
b1 -
b0 0
1"
#1540000
0"
#1545000
b10 -
b1 0
1"
#1550000
0"
#1555000
1(
1.
b1 -
b0 0
1"
#1560000
0"
#1565000
b10 -
b1 0
1"
#1570000
0"
#1575000
0(
0.
b1 -
b0 0
1"
#1580000
0"
#1585000
b10 -
b1 0
1"
#1590000
0"
#1595000
1(
1.
b1 -
b0 0
1"
#1600000
0"
#1605000
b10 -
b1 0
1"
