commonComponents.v
module lengthCounter(
    input clk,
    input halt,
    input[4:0] counterLoad,
    output reg[6:0] out
);
wire loadA;       // Bit 0 of counterLoad
wire[3:0] loadB;  // Bits 4-1 of counterLoad
assign loadA = counterLoad[0];
assign loadB = counterLoad[4:1];
wire[6:0] indexOut;

lengthIndex index(loadA, loadB, indexOut);

always @(indexOut) begin
    out <= indexOut;
end

always @(posedge clk) begin
    if(halt)
        out <= 7'h0;
    else begin
        if(out > 7'h0)
            out <= out - 7'h1;
    end
end

endmodule

////////////////////////////////////////////////////
// Length Index
////////////////////////////////////////////////////
module lengthIndex(
    input loadA,
    input[3:0] loadB,
    output reg[6:0] indexOut
);
wire[4:0] load;
assign load = {loadB,loadA};

// Lookup table
always @(load) begin
    if(loadA) begin
        if(loadB == 4'h0)
            indexOut <= 7'hfe;
        if(loadB == 4'h1)
            indexOut <= 7'h02;
        if(loadB == 4'h2)
            indexOut <= 7'h04;
        if(loadB == 4'h3)
            indexOut <= 7'h06;
        if(loadB == 4'h4)
            indexOut <= 7'h08;
        if(loadB == 4'h5)
            indexOut <= 7'h0a;
        if(loadB == 4'h6)
            indexOut <= 7'h0c;
        if(loadB == 5'h7)
            indexOut <= 7'h0E;
        if(loadB == 5'h8)
            indexOut <= 7'h10;
        if(loadB == 5'h9)
            indexOut <= 7'h12;
        if(loadB == 5'ha)
            indexOut <= 7'h14;
        if(loadB == 5'hb)
            indexOut <= 7'h16;
        if(loadB == 5'hc)
            indexOut <= 7'h18;
        if(loadB == 5'hd)
            indexOut <= 7'h1a;
        if(loadB == 5'he)
            indexOut <= 7'h1c;
        if(loadB == 5'hf)
            indexOut <= 7'h1e;
    end
    else begin
        if(loadB == 4'h0)
            indexOut <= 7'h0a;
        if(loadB == 4'h1)
            indexOut <= 7'h14;
        if(loadB == 4'h2)
            indexOut <= 7'h28;
        if(loadB == 4'h3)
            indexOut <= 7'h50;
        if(loadB == 4'h4)
            indexOut <= 7'ha0;
        if(loadB == 4'h5)
            indexOut <= 7'h3c;
        if(loadB == 4'h6)
            indexOut <= 7'h0e;
        if(loadB == 5'h7)
            indexOut <= 7'h1a;
        if(loadB == 5'h8)
            indexOut <= 7'h0c;
        if(loadB == 5'h9)
            indexOut <= 7'h18;
        if(loadB == 5'ha)
            indexOut <= 7'h30;
        if(loadB == 5'hb)
            indexOut <= 7'h60;
        if(loadB == 5'hc)
            indexOut <= 7'hc0;
        if(loadB == 5'hd)
            indexOut <= 7'h48;
        if(loadB == 5'he)
            indexOut <= 7'h10;
        if(loadB == 5'hf)
            indexOut <= 7'h20;
    end
end
endmodule

//////////////////////////////////////////////////////
// Envleope Generator
//////////////////////////////////////////////////////
module envelope(
    input clk,
    input loop,              // Controls whether the volume loops or not
    input disableFlag,       // Controls the disable
    input resetFlag,         // resetFlag==0 if the length counter is written to
    input[3:0] n,            // Period of the counter_clk. Volume defaults to n when disabled
    output reg[3:0] volume   // Output
);
reg reset;
reg[3:0] counter;
wire counter_clk; 

clkDivider divider(clk, reset, n+4'b1, counter_clk);

always @(posedge clk) begin
    if(resetFlag) begin
        counter <= 4'd15;
        reset <= 1;
    end
    else
        reset <= 0;
    if(disableFlag)
        volume <= n;
    else
        volume <= counter;
end

always @(posedge counter_clk) begin
    // If loop is set and counter is zero then it loops back to 15
    // If loop is not enabled and counter is not zero it decrements
    // If loop is not enabled, counter will decrease until it is zero
    if(loop && (counter == 0)) 
        counter <= 4'd15;
    if(counter !== 0)
        counter <= counter - 1;
end

endmodule

// Clk Divider Module, takes in clk and N(period of new clk)
// Ouputs new clk with period of N clk
module clkDivider(
    input clk,
    input rst,
    input[3:0] N,
    output clk_out
);
reg[3:0] n;
reg[3:0] r_reg;
wire[3:0] r_next;
reg clk_track;

initial begin
    n <= N/2;
    r_reg <= 0;
    clk_track <= 1'b0;
end

always @(posedge clk or posedge rst) begin
    if(rst) begin
        n <= N/2;
        r_reg <= 0;
        clk_track <= 1'b0;
    end
    else if(r_next == n) begin
        r_reg <= 0;
        clk_track <= ~clk_track;
    end
    else
        r_reg <= r_next;
end
assign r_next = r_reg+1;
assign clk_out = clk_track;
endmodule

lengthCounter.t.v
`include "commonComponents.v"

module lengthCounterTest();
reg clk, halt;
reg[4:0] counterLoad;
wire[6:0] out;

lengthCounter length(clk, halt, counterLoad, out);

initial
    clk <= 1'b0;

always begin
    #5000
    clk <= ~clk;
end

initial begin
    $dumpfile("lengthCounter.vcd");
    $dumpvars();
    assign halt = 1'b0;
    assign counterLoad = {4'ha,1'b0};
    #700000
    $finish();
end
endmodule

lengthCounter.vcd
$date
	Sun Dec  9 17:10:48 2018
$end
$version
	Icarus Verilog
$end
$timescale
	1s
$end
$scope module lengthCounterTest $end
$var wire 7 ! out [6:0] $end
$var reg 1 " clk $end
$var reg 5 # counterLoad [4:0] $end
$var reg 1 $ halt $end
$scope module length $end
$var wire 1 " clk $end
$var wire 5 % counterLoad [4:0] $end
$var wire 1 $ halt $end
$var wire 4 & loadB [3:0] $end
$var wire 1 ' loadA $end
$var wire 7 ( indexOut [6:0] $end
$var reg 7 ) out [6:0] $end
$scope module index $end
$var wire 1 ' loadA $end
$var wire 4 * loadB [3:0] $end
$var wire 5 + load [4:0] $end
$var reg 7 , indexOut [6:0] $end
$upscope $end
$upscope $end
$upscope $end
$enddefinitions $end
#0
$dumpvars
b110000 ,
b10100 +
b1010 *
b110000 )
b110000 (
0'
b1010 &
b10100 %
0$
b10100 #
0"
b110000 !
$end
#5000
b101111 !
b101111 )
1"
#10000
0"
#15000
b101110 !
b101110 )
1"
#20000
0"
#25000
b101101 !
b101101 )
1"
#30000
0"
#35000
b101100 !
b101100 )
1"
#40000
0"
#45000
b101011 !
b101011 )
1"
#50000
0"
#55000
b101010 !
b101010 )
1"
#60000
0"
#65000
b101001 !
b101001 )
1"
#70000
0"
#75000
b101000 !
b101000 )
1"
#80000
0"
#85000
b100111 !
b100111 )
1"
#90000
0"
#95000
b100110 !
b100110 )
1"
#100000
0"
#105000
b100101 !
b100101 )
1"
#110000
0"
#115000
b100100 !
b100100 )
1"
#120000
0"
#125000
b100011 !
b100011 )
1"
#130000
0"
#135000
b100010 !
b100010 )
1"
#140000
0"
#145000
b100001 !
b100001 )
1"
#150000
0"
#155000
b100000 !
b100000 )
1"
#160000
0"
#165000
b11111 !
b11111 )
1"
#170000
0"
#175000
b11110 !
b11110 )
1"
#180000
0"
#185000
b11101 !
b11101 )
1"
#190000
0"
#195000
b11100 !
b11100 )
1"
#200000
0"
#205000
b11011 !
b11011 )
1"
#210000
0"
#215000
b11010 !
b11010 )
1"
#220000
0"
#225000
b11001 !
b11001 )
1"
#230000
0"
#235000
b11000 !
b11000 )
1"
#240000
0"
#245000
b10111 !
b10111 )
1"
#250000
0"
#255000
b10110 !
b10110 )
1"
#260000
0"
#265000
b10101 !
b10101 )
1"
#270000
0"
#275000
b10100 !
b10100 )
1"
#280000
0"
#285000
b10011 !
b10011 )
1"
#290000
0"
#295000
b10010 !
b10010 )
1"
#300000
0"
#305000
b10001 !
b10001 )
1"
#310000
0"
#315000
b10000 !
b10000 )
1"
#320000
0"
#325000
b1111 !
b1111 )
1"
#330000
0"
#335000
b1110 !
b1110 )
1"
#340000
0"
#345000
b1101 !
b1101 )
1"
#350000
0"
#355000
b1100 !
b1100 )
1"
#360000
0"
#365000
b1011 !
b1011 )
1"
#370000
0"
#375000
b1010 !
b1010 )
1"
#380000
0"
#385000
b1001 !
b1001 )
1"
#390000
0"
#395000
b1000 !
b1000 )
1"
#400000
0"
#405000
b111 !
b111 )
1"
#410000
0"
#415000
b110 !
b110 )
1"
#420000
0"
#425000
b101 !
b101 )
1"
#430000
0"
#435000
b100 !
b100 )
1"
#440000
0"
#445000
b11 !
b11 )
1"
#450000
0"
#455000
b10 !
b10 )
1"
#460000
0"
#465000
b1 !
b1 )
1"
#470000
0"
#475000
b0 !
b0 )
1"
